filemetadata/__init__.py
filemetadata/admin.py
filemetadata/apps.py
filemetadata/indexer.py
filemetadata/models.py
filemetadata/tests.py
filemetadata/utils.py
filemetadata/views.py
django_filemetadata-1.0.2.dist-info/METADATA
django_filemetadata-1.0.2.dist-info/WHEEL
django_filemetadata-1.0.2.dist-info/top_level.txt
django_filemetadata-1.0.2.dist-info/RECORD
