Metadata-Version: 2.1
Name: django-filemetadata
Version: 1.0.2
Summary: Synchronize the metadata from local files in the DB
Home-page: https://gitlab.com/rristow/django-filemetadata
Author: Rodrigo Ristow
Author-email: rodrigo@maxttor.com
License: BSD
Keywords: django file metadata
Platform: UNKNOWN
Classifier: Development Status :: 3 - Alpha
Classifier: Topic :: Utilities
Classifier: License :: OSI Approved :: BSD License
